LICENSE
README.md
pyproject.toml
setup.py
aioheleket/__init__.py
aioheleket.egg-info/PKG-INFO
aioheleket.egg-info/SOURCES.txt
aioheleket.egg-info/dependency_links.txt
aioheleket.egg-info/requires.txt
aioheleket.egg-info/top_level.txt
aioheleket/services/__init__.py
aioheleket/services/finance_service.py
aioheleket/services/payment_service.py
aioheleket/services/payout_service.py
aioheleket/services/wallet_service.py
aioheleket/types/__init__.py
aioheleket/types/client.py
aioheleket/utils/__init__.py
aioheleket/utils/data_classes.py
aioheleket/utils/enums.py
aioheleket/utils/exceptions.py
aioheleket/utils/request_builder.py
aioheleket/utils/schemas.py