Metadata-Version: 2.4
Name: aioheleket
Version: 1.1.0
Summary: Asynchronous Python library for Heleket API
Home-page: https://github.com/SuperFeda/aioheleket
Download-URL: https://github.com/SuperFeda/aioheleket
Author: SuperFeda
License-Expression: MIT
Project-URL: homepage, https://github.com/SuperFeda/aioheleket
Project-URL: documentation, https://github.com/SuperFeda/aioheleket
Project-URL: source, https://github.com/SuperFeda/aioheleket
Project-URL: tracker, https://github.com/SuperFeda/aioheleket/issues
Requires-Python: >=3.10
License-File: LICENSE
Requires-Dist: aiohttp>=3.12
Requires-Dist: pydantic>=2.11
Provides-Extra: dev
Requires-Dist: setuptools>=80.9; extra == "dev"
Requires-Dist: twine>=6.2; extra == "dev"
Dynamic: download-url
Dynamic: home-page
Dynamic: license-file
Dynamic: requires-python
